paperless/__init__.py
paperless/__main__.py
paperless/constants.py
paperless/paperless.py
paperless/version.py
paperless/kernels/__init__.py
paperless/kernels/kernel_client.py
paperless/kernels/kernel_manager.py
paperless/notebook/__init__.py
paperless/notebook/notebook_manager.py
paperless/serverless/__init__.py
paperless/serverless/serverless_manager.py
paperless-1.5.3.dist-info/LICENSE
paperless-1.5.3.dist-info/METADATA
paperless-1.5.3.dist-info/WHEEL
paperless-1.5.3.dist-info/entry_points.txt
paperless-1.5.3.dist-info/top_level.txt
paperless-1.5.3.dist-info/RECORD
