Metadata-Version: 2.1
Name: paperless
Version: 1.5.3
Summary: A papermill implementation to run notebooks inside dataproc serverless
Classifier: Programming Language :: Python :: 3.8
Classifier: Operating System :: OS Independent
Requires-Python: >=3.10
License-File: LICENSE
Requires-Dist: papermill
Requires-Dist: dataproc-jupyter-plugin
Requires-Dist: pytest
Requires-Dist: loguru
Requires-Dist: gcsfs
Requires-Dist: click
Requires-Dist: jupyter-client
